meuip/__init__.py
meuip/command_line.py
meuip-0.0.3.dist-info/METADATA
meuip-0.0.3.dist-info/WHEEL
meuip-0.0.3.dist-info/entry_points.txt
meuip-0.0.3.dist-info/top_level.txt
meuip-0.0.3.dist-info/RECORD
