Metadata-Version: 2.1
Name: meuip
Version: 0.0.3
Summary: command line to know your IP, isp, location and others
Home-page: UNKNOWN
Author: rafaelscone (Rafael Schneider)
Author-email: <pipmeuip@impaire.com>
License: UNKNOWN
Keywords: ip location,ip,region,asn
Platform: UNKNOWN
Classifier: Development Status :: 1 - Planning
Classifier: Intended Audience :: Developers
Classifier: Programming Language :: Python :: 3
Classifier: Operating System :: Unix
Classifier: Operating System :: MacOS :: MacOS X
Classifier: Operating System :: Microsoft :: Windows
Requires-Dist: requests
